toscaparser/__init__.py
toscaparser/capabilities.py
toscaparser/dataentity.py
toscaparser/entity_template.py
toscaparser/functions.py
toscaparser/groups.py
toscaparser/imports.py
toscaparser/nodetemplate.py
toscaparser/parameters.py
toscaparser/policy.py
toscaparser/properties.py
toscaparser/relationship_template.py
toscaparser/repositories.py
toscaparser/shell.py
toscaparser/substitution_mappings.py
toscaparser/topology_template.py
toscaparser/tosca_template.py
toscaparser/tpl_relationship_graph.py
toscaparser/triggers.py
toscaparser/unsupportedtype.py
toscaparser/common/__init__.py
toscaparser/common/exception.py
toscaparser/elements/TOSCA_definition_1_0.yaml
toscaparser/elements/__init__.py
toscaparser/elements/artifacttype.py
toscaparser/elements/attribute_definition.py
toscaparser/elements/capabilitytype.py
toscaparser/elements/constraints.py
toscaparser/elements/datatype.py
toscaparser/elements/entity_type.py
toscaparser/elements/grouptype.py
toscaparser/elements/interfaces.py
toscaparser/elements/nodetype.py
toscaparser/elements/policytype.py
toscaparser/elements/portspectype.py
toscaparser/elements/property_definition.py
toscaparser/elements/relationshiptype.py
toscaparser/elements/scalarunit.py
toscaparser/elements/statefulentitytype.py
toscaparser/elements/tosca_type_validation.py
toscaparser/extensions/__init__.py
toscaparser/extensions/exttools.py
toscaparser/extensions/nfv/TOSCA_nfv_definition_1_0_0.yaml
toscaparser/extensions/nfv/__init__.py
toscaparser/extensions/nfv/tosca_simple_profile_for_nfv_1_0_0.py
toscaparser/extensions/nfv/tests/__init__.py
toscaparser/extensions/nfv/tests/test_tosca_nfv_tpl.py
toscaparser/extensions/nfv/tests/test_tosca_vRNC.py
toscaparser/extensions/nfv/tests/data/tosca_helloworld_nfv.yaml
toscaparser/extensions/nfv/tests/data/vRNC/README.txt
toscaparser/extensions/nfv/tests/data/vRNC/Definitions/rnc_definition.yaml
toscaparser/extensions/nfv/tests/data/vRNC/Definitions/vRNC.yaml
nfv_toscaparser-1.1.1.dist-info/AUTHORS
nfv_toscaparser-1.1.1.dist-info/LICENSE
nfv_toscaparser-1.1.1.dist-info/METADATA
nfv_toscaparser-1.1.1.dist-info/WHEEL
nfv_toscaparser-1.1.1.dist-info/entry_points.txt
nfv_toscaparser-1.1.1.dist-info/pbr.json
nfv_toscaparser-1.1.1.dist-info/top_level.txt
nfv_toscaparser-1.1.1.dist-info/RECORD
