Metadata-Version: 2.1
Name: nfv-toscaparser
Version: 1.1.1
Summary: Parser for nfv tosca and TOSCA Simple Profile in YAML.
Home-page: https://wiki.opnfv.org/display/parser
Author: OPNFV
Author-email: opnfv-dev@lists.opnfv.org
License: Apache-2.0
Platform: UNKNOWN
Classifier: Environment :: Plugins
Classifier: Intended Audience :: Information Technology
Classifier: Intended Audience :: System Administrators
Classifier: License :: OSI Approved :: Apache Software License
Classifier: Operating System :: POSIX :: Linux
Classifier: Programming Language :: Python
Classifier: Programming Language :: Python :: 2
Classifier: Programming Language :: Python :: 2.7
Classifier: Programming Language :: Python :: 3
Classifier: Programming Language :: Python :: 3.4
Classifier: Programming Language :: Python :: 3.5
Requires-Dist: pbr (!=2.1.0,>=2.0.0)
Requires-Dist: Babel (!=2.4.0,>=2.3.4)
Requires-Dist: cliff (>=2.8.0)
Requires-Dist: PyYAML (>=3.10.0)
Requires-Dist: python-dateutil (>=2.4.2)
Requires-Dist: six (>=1.9.0)
Requires-Dist: requests (>=2.14.2)
